fastlogfileparser/cosmors/__init__.py
fastlogfileparser/cosmors/fast_cosmors_logfile_parser.py
fastlogfileparser/cosmors/utils/postprocessing.py
fastlogfileparser/cosmors/utils/regexes.py
fastlogfileparser/gaussian/__init__.py
fastlogfileparser/gaussian/fast_gaussian_logfile_parser.py
fastlogfileparser/gaussian/utils/postprocessing.py
fastlogfileparser/gaussian/utils/preprocessing.py
fastlogfileparser/gaussian/utils/regexes.py
fastlogfileparser/generic/__init__.py
fastlogfileparser/generic/iter_patterns.py
fastlogfileparser/generic/postprocessing.py
fastlogfileparser/orca/__init__.py
fastlogfileparser/orca/fast_orca_logfile_parser.py
fastlogfileparser/orca/utils/postprocessing.py
fastlogfileparser/orca/utils/regexes.py
fastlogfileparser-1.0.0.dist-info/METADATA
fastlogfileparser-1.0.0.dist-info/WHEEL
fastlogfileparser-1.0.0.dist-info/top_level.txt
fastlogfileparser-1.0.0.dist-info/RECORD
