Metadata-Version: 2.4
Name: fastlogfileparser
Version: 1.0.0
Summary: Parse computational chemistry log files, but fast-ly.
Author: Jackson Burns
License: MIT
Project-URL: Homepage, https://github.com/QuantumPioneer/FastLogfileParser
Classifier: Programming Language :: Python :: 3
Requires-Python: >=3.8
Provides-Extra: dev
Requires-Dist: black; extra == "dev"
Requires-Dist: isort; extra == "dev"
Requires-Dist: pytest; extra == "dev"
Requires-Dist: pytest-dependency; extra == "dev"
Provides-Extra: demos
Requires-Dist: ase; extra == "demos"
Requires-Dist: cclib; extra == "demos"
